{
  "exported_at": "2026-05-14T23:13:56.422Z",
  "source": "supabase production",
  "note": "Backup taken before dropping lite_* tables. Source code available at git tag archive/nudge-lite-spike.",
  "tables": {
    "lite_profiles": [
      {
        "sns_type": "discord",
        "sns_id": "1468562237852483682",
        "subscription_status": "active",
        "updated_at": "2026-03-03T09:18:17.976Z",
        "created_at": "2026-03-03T09:18:17.976Z"
      }
    ],
    "lite_content_progress": [
      {
        "progress_id": "1",
        "sns_type": "discord",
        "sns_id": "1468562237852483682",
        "learning_product_id": "770c0442-1d0f-4d84-a998-5cef8190a9a3",
        "current_content_id": "550e8400-e29b-41d4-a716-446655440000",
        "last_card_id": null,
        "completed_cards_count": 0,
        "total_cards_count": 10,
        "last_feedback_score": null,
        "updated_at": "2026-03-03T09:18:18.737Z",
        "created_at": "2026-03-03T09:18:18.737Z"
      }
    ],
    "lite_card_deliveries": []
  }
}